{
    "filename": "IMG_0729.jpg",
    "datas": [
        {
            "BoundingBox": {
                "Width": 0.3111383616924286,
                "Height": 0.33536621928215027,
                "Left": 0.3325559198856354,
                "Top": 0.2294059842824936
            },
            "AgeRange": {
                "Low": 26,
                "High": 43
            },
            "Smile": {
                "Value": false,
                "Confidence": 99.28244018554688
            },
            "Eyeglasses": {
                "Value": false,
                "Confidence": 99.9911880493164
            },
            "Sunglasses": {
                "Value": false,
                "Confidence": 99.9995346069336
            },
            "Gender": {
                "Value": "Male",
                "Confidence": 87.14764404296875
            },
            "Beard": {
                "Value": false,
                "Confidence": 99.31092071533203
            },
            "Mustache": {
                "Value": false,
                "Confidence": 99.97818756103516
            },
            "EyesOpen": {
                "Value": true,
                "Confidence": 99.99549102783203
            },
            "MouthOpen": {
                "Value": false,
                "Confidence": 99.53469848632812
            },
            "Emotions": [
                {
                    "Type": "HAPPY",
                    "Confidence": 0.6726683378219604
                },
                {
                    "Type": "SURPRISED",
                    "Confidence": 2.540369987487793
                },
                {
                    "Type": "DISGUSTED",
                    "Confidence": 4.280856132507324
                },
                {
                    "Type": "SAD",
                    "Confidence": 1.7339866161346436
                },
                {
                    "Type": "CALM",
                    "Confidence": 74.11505889892578
                },
                {
                    "Type": "CONFUSED",
                    "Confidence": 0
                },
                {
                    "Type": "ANGRY",
                    "Confidence": 8.244166374206543
                }
            ],
            "Landmarks": [
                {
                    "Type": "eyeLeft",
                    "X": 0.418172150850296,
                    "Y": 0.3723074793815613
                },
                {
                    "Type": "eyeRight",
                    "X": 0.562067985534668,
                    "Y": 0.3694048821926117
                },
                {
                    "Type": "mouthLeft",
                    "X": 0.4373753070831299,
                    "Y": 0.48613548278808594
                },
                {
                    "Type": "mouthRight",
                    "X": 0.5553656816482544,
                    "Y": 0.48396429419517517
                },
                {
                    "Type": "nose",
                    "X": 0.48870906233787537,
                    "Y": 0.4335125684738159
                },
                {
                    "Type": "leftEyeBrowLeft",
                    "X": 0.36084312200546265,
                    "Y": 0.3470544219017029
                },
                {
                    "Type": "leftEyeBrowRight",
                    "X": 0.4438730478286743,
                    "Y": 0.3392382264137268
                },
                {
                    "Type": "leftEyeBrowUp",
                    "X": 0.40134385228157043,
                    "Y": 0.3343243896961212
                },
                {
                    "Type": "rightEyeBrowLeft",
                    "X": 0.5286863446235657,
                    "Y": 0.3374404013156891
                },
                {
                    "Type": "rightEyeBrowRight",
                    "X": 0.6196034550666809,
                    "Y": 0.34148406982421875
                },
                {
                    "Type": "rightEyeBrowUp",
                    "X": 0.5726242661476135,
                    "Y": 0.3302744925022125
                },
                {
                    "Type": "leftEyeLeft",
                    "X": 0.3927185535430908,
                    "Y": 0.3716893494129181
                },
                {
                    "Type": "leftEyeRight",
                    "X": 0.44598811864852905,
                    "Y": 0.37252044677734375
                },
                {
                    "Type": "leftEyeUp",
                    "X": 0.41669219732284546,
                    "Y": 0.3668496906757355
                },
                {
                    "Type": "leftEyeDown",
                    "X": 0.4183654189109802,
                    "Y": 0.37691760063171387
                },
                {
                    "Type": "rightEyeLeft",
                    "X": 0.5323736071586609,
                    "Y": 0.37069427967071533
                },
                {
                    "Type": "rightEyeRight",
                    "X": 0.5866797566413879,
                    "Y": 0.3676225543022156
                },
                {
                    "Type": "rightEyeUp",
                    "X": 0.5605113506317139,
                    "Y": 0.36383190751075745
                },
                {
                    "Type": "rightEyeDown",
                    "X": 0.5602083206176758,
                    "Y": 0.373959481716156
                },
                {
                    "Type": "noseLeft",
                    "X": 0.464853435754776,
                    "Y": 0.44623833894729614
                },
                {
                    "Type": "noseRight",
                    "X": 0.5184764862060547,
                    "Y": 0.4430631399154663
                },
                {
                    "Type": "mouthUp",
                    "X": 0.49236780405044556,
                    "Y": 0.4707675278186798
                },
                {
                    "Type": "mouthDown",
                    "X": 0.4947595000267029,
                    "Y": 0.5034292936325073
                },
                {
                    "Type": "leftPupil",
                    "X": 0.418172150850296,
                    "Y": 0.3723074793815613
                },
                {
                    "Type": "rightPupil",
                    "X": 0.562067985534668,
                    "Y": 0.3694048821926117
                },
                {
                    "Type": "upperJawlineLeft",
                    "X": 0.33392462134361267,
                    "Y": 0.3706851601600647
                },
                {
                    "Type": "midJawlineLeft",
                    "X": 0.3712364137172699,
                    "Y": 0.4906778335571289
                },
                {
                    "Type": "chinBottom",
                    "X": 0.4999261498451233,
                    "Y": 0.5590124726295471
                },
                {
                    "Type": "midJawlineRight",
                    "X": 0.6337239742279053,
                    "Y": 0.48505663871765137
                },
                {
                    "Type": "upperJawlineRight",
                    "X": 0.6605842709541321,
                    "Y": 0.36366891860961914
                }
            ],
            "Pose": {
                "Roll": -2.5586931705474854,
                "Yaw": -7.39712381362915,
                "Pitch": -12.635927200317383
            },
            "Quality": {
                "Brightness": 63.14633560180664,
                "Sharpness": 89.85481262207031
            },
            "Confidence": 100
        }
    ]
}